steering_generator/__init__.py
steering_generator/__main__.py
steering_generator/analyzer.py
steering_generator/deep_analyzer.py
steering_generator/detector.py
steering_generator/generator.py
steering_generator/server.py
steering_generator_mcp-0.1.3.dist-info/METADATA
steering_generator_mcp-0.1.3.dist-info/WHEEL
steering_generator_mcp-0.1.3.dist-info/entry_points.txt
steering_generator_mcp-0.1.3.dist-info/licenses/LICENSE
steering_generator_mcp-0.1.3.dist-info/RECORD
