Metadata-Version: 2.4
Name: steering-generator-mcp
Version: 0.1.3
Summary: MCP Server to auto-generate steering/context docs from codebases - like Kiro IDE's built-in feature, but for all AI IDEs
Project-URL: Homepage, https://github.com/yourusername/steering-generator-mcp
Project-URL: Repository, https://github.com/yourusername/steering-generator-mcp
Project-URL: Issues, https://github.com/yourusername/steering-generator-mcp/issues
Author: Your Name
License: MIT
License-File: LICENSE
Keywords: ai,context,copilot,cursor,documentation,ide,kiro,laravel,mcp,nextjs,react,steering,vue
Classifier: Development Status :: 4 - Beta
Classifier: Intended Audience :: Developers
Classifier: License :: OSI Approved :: MIT License
Classifier: Programming Language :: Python :: 3
Classifier: Programming Language :: Python :: 3.10
Classifier: Programming Language :: Python :: 3.11
Classifier: Programming Language :: Python :: 3.12
Classifier: Topic :: Software Development :: Code Generators
Classifier: Topic :: Software Development :: Documentation
Requires-Python: >=3.10
Requires-Dist: fastmcp>=2.0.0
